README.rst
setup.py
sqlalchemy_audit/__init__.py
sqlalchemy_audit/versioned.py
sqlalchemy_audit.egg-info/PKG-INFO
sqlalchemy_audit.egg-info/SOURCES.txt
sqlalchemy_audit.egg-info/dependency_links.txt
sqlalchemy_audit.egg-info/requires.txt
sqlalchemy_audit.egg-info/top_level.txt
sqlalchemy_audit.egg-info/zip-safe
sqlalchemy_audit/test/__init__.py
sqlalchemy_audit/test/test_versioned.py