Metadata-Version: 1.1
Name: sqlalchemy-audit
Version: 0.1.0
Summary: sqlalchemy-audit provides an easy way to set up revision tracking for your data.
Home-page: https://github.com/canaryhealth/sqlalchemy_audit
Author: UNKNOWN
Author-email: UNKNOWN
License: MIT
Platform: any
Classifier: Development Status :: 5 - Production/Stable
Classifier: Environment :: Web Environment
Classifier: Intended Audience :: Developers
Classifier: License :: OSI Approved :: MIT License
Classifier: Natural Language :: English
Classifier: Operating System :: OS Independent
Classifier: Programming Language :: Python
Classifier: Topic :: Database
